{
  "openapi": "3.0.1",
  "info": {
    "title": "Interview Simulator",
    "version": "1.0"
  },
  "paths": {
    "/api/admin/domains/create": {
      "post": {
        "tags": [
          "Admin"
        ],
        "requestBody": {
          "content": {
            "multipart/form-data": {
              "schema": {
                "type": "object",
                "properties": {
                  "Name": {
                    "type": "string"
                  },
                  "Logo": {
                    "type": "string",
                    "format": "binary"
                  }
                }
              },
              "encoding": {
                "Name": {
                  "style": "form"
                },
                "Logo": {
                  "style": "form"
                }
              }
            }
          }
        },
        "responses": {
          "200": {
            "description": "OK"
          }
        }
      }
    },
    "/api/admin/domains/all": {
      "get": {
        "tags": [
          "Admin"
        ],
        "responses": {
          "200": {
            "description": "OK"
          }
        }
      }
    },
    "/api/admin/domains/{domainId}/delete": {
      "delete": {
        "tags": [
          "Admin"
        ],
        "parameters": [
          {
            "name": "domainId",
            "in": "path",
            "required": true,
            "schema": {
              "type": "string",
              "format": "uuid"
            }
          }
        ],
        "responses": {
          "200": {
            "description": "OK"
          }
        }
      }
    },
    "/api/admin/domains/questions/create": {
      "post": {
        "tags": [
          "Admin"
        ],
        "requestBody": {
          "content": {
            "application/json": {
              "schema": {
                "$ref": "#/components/schemas/CreateQuestionDto"
              }
            },
            "text/json": {
              "schema": {
                "$ref": "#/components/schemas/CreateQuestionDto"
              }
            },
            "application/*+json": {
              "schema": {
                "$ref": "#/components/schemas/CreateQuestionDto"
              }
            }
          }
        },
        "responses": {
          "200": {
            "description": "OK"
          }
        }
      }
    },
    "/api/admin/domains/{domainId}/questions": {
      "get": {
        "tags": [
          "Admin"
        ],
        "parameters": [
          {
            "name": "domainId",
            "in": "path",
            "required": true,
            "schema": {
              "type": "string",
              "format": "uuid"
            }
          }
        ],
        "responses": {
          "200": {
            "description": "OK"
          }
        }
      }
    },
    "/api/admin/domains/questions/{questionId}/update": {
      "put": {
        "tags": [
          "Admin"
        ],
        "parameters": [
          {
            "name": "questionId",
            "in": "path",
            "required": true,
            "schema": {
              "type": "string",
              "format": "uuid"
            }
          }
        ],
        "requestBody": {
          "content": {
            "application/json": {
              "schema": {
                "$ref": "#/components/schemas/UpdateQuestionDto"
              }
            },
            "text/json": {
              "schema": {
                "$ref": "#/components/schemas/UpdateQuestionDto"
              }
            },
            "application/*+json": {
              "schema": {
                "$ref": "#/components/schemas/UpdateQuestionDto"
              }
            }
          }
        },
        "responses": {
          "200": {
            "description": "OK"
          }
        }
      }
    },
    "/api/admin/domains/questions/{questionId}/delete": {
      "delete": {
        "tags": [
          "Admin"
        ],
        "parameters": [
          {
            "name": "questionId",
            "in": "path",
            "required": true,
            "schema": {
              "type": "string",
              "format": "uuid"
            }
          }
        ],
        "responses": {
          "200": {
            "description": "OK"
          }
        }
      }
    },
    "/api/admin/domains/questions/{questionId}/difficulty": {
      "patch": {
        "tags": [
          "Admin"
        ],
        "parameters": [
          {
            "name": "questionId",
            "in": "path",
            "required": true,
            "schema": {
              "type": "string",
              "format": "uuid"
            }
          },
          {
            "name": "difficulty",
            "in": "query",
            "schema": {
              "$ref": "#/components/schemas/Difficulty"
            }
          }
        ],
        "responses": {
          "200": {
            "description": "OK"
          }
        }
      }
    },
    "/api/admin/domains/{domainId}": {
      "put": {
        "tags": [
          "Admin"
        ],
        "parameters": [
          {
            "name": "domainId",
            "in": "path",
            "required": true,
            "schema": {
              "type": "string",
              "format": "uuid"
            }
          }
        ],
        "requestBody": {
          "content": {
            "multipart/form-data": {
              "schema": {
                "type": "object",
                "properties": {
                  "Id": {
                    "type": "string",
                    "format": "uuid"
                  },
                  "Name": {
                    "type": "string"
                  },
                  "Logo": {
                    "type": "string",
                    "format": "binary"
                  }
                }
              },
              "encoding": {
                "Id": {
                  "style": "form"
                },
                "Name": {
                  "style": "form"
                },
                "Logo": {
                  "style": "form"
                }
              }
            }
          }
        },
        "responses": {
          "200": {
            "description": "OK"
          }
        }
      }
    },
    "/api/admin/domains/{domainId}/configuration": {
      "get": {
        "tags": [
          "Admin"
        ],
        "parameters": [
          {
            "name": "domainId",
            "in": "path",
            "required": true,
            "schema": {
              "type": "string",
              "format": "uuid"
            }
          }
        ],
        "responses": {
          "200": {
            "description": "OK"
          }
        }
      },
      "put": {
        "tags": [
          "Admin"
        ],
        "parameters": [
          {
            "name": "domainId",
            "in": "path",
            "required": true,
            "schema": {
              "type": "string",
              "format": "uuid"
            }
          }
        ],
        "requestBody": {
          "content": {
            "application/json": {
              "schema": {
                "$ref": "#/components/schemas/UpdateDomainConfigurationDto"
              }
            },
            "text/json": {
              "schema": {
                "$ref": "#/components/schemas/UpdateDomainConfigurationDto"
              }
            },
            "application/*+json": {
              "schema": {
                "$ref": "#/components/schemas/UpdateDomainConfigurationDto"
              }
            }
          }
        },
        "responses": {
          "200": {
            "description": "OK"
          }
        }
      }
    },
    "/api/admin/dashboard/stats/domains/count": {
      "get": {
        "tags": [
          "Admin"
        ],
        "responses": {
          "200": {
            "description": "OK"
          }
        }
      }
    },
    "/api/admin/dashboard/stats/questions/count": {
      "get": {
        "tags": [
          "Admin"
        ],
        "responses": {
          "200": {
            "description": "OK"
          }
        }
      }
    },
    "/api/admin/dashboard/stats/companies/count": {
      "get": {
        "tags": [
          "Admin"
        ],
        "responses": {
          "200": {
            "description": "OK"
          }
        }
      }
    },
    "/api/admin/dashboard/activity/recent": {
      "get": {
        "tags": [
          "Admin"
        ],
        "parameters": [
          {
            "name": "limit",
            "in": "query",
            "schema": {
              "type": "integer",
              "format": "int32",
              "default": 10
            }
          }
        ],
        "responses": {
          "200": {
            "description": "OK"
          }
        }
      }
    },
    "/api/admin/users/companies": {
      "get": {
        "tags": [
          "Admin"
        ],
        "responses": {
          "200": {
            "description": "OK"
          }
        }
      }
    },
    "/api/admin/users/companies/{companyId}": {
      "delete": {
        "tags": [
          "Admin"
        ],
        "parameters": [
          {
            "name": "companyId",
            "in": "path",
            "required": true,
            "schema": {
              "type": "string",
              "format": "uuid"
            }
          }
        ],
        "responses": {
          "200": {
            "description": "OK"
          }
        }
      }
    },
    "/api/admin/users/admins": {
      "post": {
        "tags": [
          "Admin"
        ],
        "requestBody": {
          "content": {
            "application/json": {
              "schema": {
                "$ref": "#/components/schemas/CreateAdminDto"
              }
            },
            "text/json": {
              "schema": {
                "$ref": "#/components/schemas/CreateAdminDto"
              }
            },
            "application/*+json": {
              "schema": {
                "$ref": "#/components/schemas/CreateAdminDto"
              }
            }
          }
        },
        "responses": {
          "200": {
            "description": "OK"
          }
        }
      },
      "get": {
        "tags": [
          "Admin"
        ],
        "responses": {
          "200": {
            "description": "OK"
          }
        }
      }
    },
    "/api/admin/dashboard/stats/users/regular/count": {
      "get": {
        "tags": [
          "Admin"
        ],
        "responses": {
          "200": {
            "description": "OK"
          }
        }
      }
    },
    "/api/admin/dashboard/stats/sessions/count": {
      "get": {
        "tags": [
          "Admin"
        ],
        "responses": {
          "200": {
            "description": "OK"
          }
        }
      }
    },
    "/api/admin/dashboard/stats/company-sessions/count": {
      "get": {
        "tags": [
          "Admin"
        ],
        "responses": {
          "200": {
            "description": "OK"
          }
        }
      }
    },
    "/api/admin/users/admins/{adminId}": {
      "delete": {
        "tags": [
          "Admin"
        ],
        "parameters": [
          {
            "name": "adminId",
            "in": "path",
            "required": true,
            "schema": {
              "type": "string",
              "format": "uuid"
            }
          }
        ],
        "responses": {
          "200": {
            "description": "OK"
          }
        }
      }
    },
    "/api/Auth/register": {
      "post": {
        "tags": [
          "Auth"
        ],
        "requestBody": {
          "content": {
            "multipart/form-data": {
              "schema": {
                "required": [
                  "Email",
                  "Password",
                  "UserType"
                ],
                "type": "object",
                "properties": {
                  "Email": {
                    "type": "string",
                    "format": "email"
                  },
                  "Password": {
                    "type": "string"
                  },
                  "UserType": {
                    "$ref": "#/components/schemas/UserType"
                  },
                  "FirstName": {
                    "type": "string"
                  },
                  "LastName": {
                    "type": "string"
                  },
                  "CompanyName": {
                    "type": "string"
                  },
                  "LogoFile": {
                    "type": "string",
                    "format": "binary"
                  },
                  "Department": {
                    "type": "string"
                  }
                }
              },
              "encoding": {
                "Email": {
                  "style": "form"
                },
                "Password": {
                  "style": "form"
                },
                "UserType": {
                  "style": "form"
                },
                "FirstName": {
                  "style": "form"
                },
                "LastName": {
                  "style": "form"
                },
                "CompanyName": {
                  "style": "form"
                },
                "LogoFile": {
                  "style": "form"
                },
                "Department": {
                  "style": "form"
                }
              }
            }
          }
        },
        "responses": {
          "200": {
            "description": "OK"
          }
        }
      }
    },
    "/api/Auth/login": {
      "post": {
        "tags": [
          "Auth"
        ],
        "requestBody": {
          "content": {
            "application/json": {
              "schema": {
                "$ref": "#/components/schemas/LoginDto"
              }
            },
            "text/json": {
              "schema": {
                "$ref": "#/components/schemas/LoginDto"
              }
            },
            "application/*+json": {
              "schema": {
                "$ref": "#/components/schemas/LoginDto"
              }
            }
          }
        },
        "responses": {
          "200": {
            "description": "OK"
          }
        }
      }
    },
    "/api/candidate-interview/start/{token}": {
      "post": {
        "tags": [
          "CandidateInterview"
        ],
        "parameters": [
          {
            "name": "token",
            "in": "path",
            "required": true,
            "schema": {
              "type": "string"
            }
          }
        ],
        "requestBody": {
          "content": {
            "application/json": {
              "schema": {
                "$ref": "#/components/schemas/StartCandidateInterviewRequest"
              }
            },
            "text/json": {
              "schema": {
                "$ref": "#/components/schemas/StartCandidateInterviewRequest"
              }
            },
            "application/*+json": {
              "schema": {
                "$ref": "#/components/schemas/StartCandidateInterviewRequest"
              }
            }
          }
        },
        "responses": {
          "200": {
            "description": "OK"
          }
        }
      }
    },
    "/api/candidate-interview/submit-response": {
      "post": {
        "tags": [
          "CandidateInterview"
        ],
        "requestBody": {
          "content": {
            "multipart/form-data": {
              "schema": {
                "type": "object",
                "properties": {
                  "SessionId": {
                    "type": "string",
                    "format": "uuid"
                  },
                  "QuestionOrder": {
                    "type": "integer",
                    "format": "int32"
                  },
                  "AudioResponse": {
                    "type": "string",
                    "format": "binary"
                  }
                }
              },
              "encoding": {
                "SessionId": {
                  "style": "form"
                },
                "QuestionOrder": {
                  "style": "form"
                },
                "AudioResponse": {
                  "style": "form"
                }
              }
            }
          }
        },
        "responses": {
          "200": {
            "description": "OK"
          }
        }
      }
    },
    "/api/candidate-interview/next-question": {
      "post": {
        "tags": [
          "CandidateInterview"
        ],
        "requestBody": {
          "content": {
            "application/json": {
              "schema": {
                "$ref": "#/components/schemas/NextCandidateQuestionRequest"
              }
            },
            "text/json": {
              "schema": {
                "$ref": "#/components/schemas/NextCandidateQuestionRequest"
              }
            },
            "application/*+json": {
              "schema": {
                "$ref": "#/components/schemas/NextCandidateQuestionRequest"
              }
            }
          }
        },
        "responses": {
          "200": {
            "description": "OK"
          }
        }
      }
    },
    "/api/company-interview/create": {
      "post": {
        "tags": [
          "CompanyInterview"
        ],
        "requestBody": {
          "content": {
            "application/json": {
              "schema": {
                "$ref": "#/components/schemas/CreateCompanyInterviewRequest"
              }
            },
            "text/json": {
              "schema": {
                "$ref": "#/components/schemas/CreateCompanyInterviewRequest"
              }
            },
            "application/*+json": {
              "schema": {
                "$ref": "#/components/schemas/CreateCompanyInterviewRequest"
              }
            }
          }
        },
        "responses": {
          "200": {
            "description": "OK"
          }
        }
      }
    },
    "/api/company-interview/{interviewId}/invite": {
      "post": {
        "tags": [
          "CompanyInterview"
        ],
        "parameters": [
          {
            "name": "interviewId",
            "in": "path",
            "required": true,
            "schema": {
              "type": "string",
              "format": "uuid"
            }
          }
        ],
        "requestBody": {
          "content": {
            "application/json": {
              "schema": {
                "$ref": "#/components/schemas/InviteCandidatesRequest"
              }
            },
            "text/json": {
              "schema": {
                "$ref": "#/components/schemas/InviteCandidatesRequest"
              }
            },
            "application/*+json": {
              "schema": {
                "$ref": "#/components/schemas/InviteCandidatesRequest"
              }
            }
          }
        },
        "responses": {
          "200": {
            "description": "OK"
          }
        }
      }
    },
    "/api/company-interview/{interviewId}/finish": {
      "post": {
        "tags": [
          "CompanyInterview"
        ],
        "parameters": [
          {
            "name": "interviewId",
            "in": "path",
            "required": true,
            "schema": {
              "type": "string",
              "format": "uuid"
            }
          }
        ],
        "responses": {
          "200": {
            "description": "OK"
          }
        }
      }
    },
    "/api/company-interview/results/{interviewId}": {
      "get": {
        "tags": [
          "CompanyInterview"
        ],
        "parameters": [
          {
            "name": "interviewId",
            "in": "path",
            "required": true,
            "schema": {
              "type": "string",
              "format": "uuid"
            }
          }
        ],
        "responses": {
          "200": {
            "description": "OK"
          }
        }
      }
    },
    "/api/company-interview/list": {
      "get": {
        "tags": [
          "CompanyInterview"
        ],
        "responses": {
          "200": {
            "description": "OK"
          }
        }
      }
    },
    "/api/company-interview/{interviewId}": {
      "get": {
        "tags": [
          "CompanyInterview"
        ],
        "parameters": [
          {
            "name": "interviewId",
            "in": "path",
            "required": true,
            "schema": {
              "type": "string",
              "format": "uuid"
            }
          }
        ],
        "responses": {
          "200": {
            "description": "OK"
          }
        }
      },
      "delete": {
        "tags": [
          "CompanyInterview"
        ],
        "parameters": [
          {
            "name": "interviewId",
            "in": "path",
            "required": true,
            "schema": {
              "type": "string",
              "format": "uuid"
            }
          }
        ],
        "responses": {
          "200": {
            "description": "OK"
          }
        }
      }
    },
    "/api/company-interview/session/{sessionId}": {
      "get": {
        "tags": [
          "CompanyInterview"
        ],
        "parameters": [
          {
            "name": "sessionId",
            "in": "path",
            "required": true,
            "schema": {
              "type": "string",
              "format": "uuid"
            }
          }
        ],
        "responses": {
          "200": {
            "description": "OK"
          }
        }
      }
    },
    "/api/company-interview/session/{sessionId}/save": {
      "post": {
        "tags": [
          "CompanyInterview"
        ],
        "parameters": [
          {
            "name": "sessionId",
            "in": "path",
            "required": true,
            "schema": {
              "type": "string",
              "format": "uuid"
            }
          }
        ],
        "responses": {
          "200": {
            "description": "OK"
          }
        }
      }
    },
    "/api/company-interview/saved/{savedCandidateId}": {
      "delete": {
        "tags": [
          "CompanyInterview"
        ],
        "parameters": [
          {
            "name": "savedCandidateId",
            "in": "path",
            "required": true,
            "schema": {
              "type": "string",
              "format": "uuid"
            }
          }
        ],
        "responses": {
          "200": {
            "description": "OK"
          }
        }
      }
    },
    "/api/company-interview/saved": {
      "get": {
        "tags": [
          "CompanyInterview"
        ],
        "responses": {
          "200": {
            "description": "OK"
          }
        }
      }
    },
    "/api/interview/domains": {
      "get": {
        "tags": [
          "PublicInterview"
        ],
        "responses": {
          "200": {
            "description": "OK"
          }
        }
      }
    },
    "/api/interview/start": {
      "post": {
        "tags": [
          "PublicInterview"
        ],
        "requestBody": {
          "content": {
            "application/json": {
              "schema": {
                "$ref": "#/components/schemas/StartRequest"
              }
            },
            "text/json": {
              "schema": {
                "$ref": "#/components/schemas/StartRequest"
              }
            },
            "application/*+json": {
              "schema": {
                "$ref": "#/components/schemas/StartRequest"
              }
            }
          }
        },
        "responses": {
          "200": {
            "description": "OK"
          }
        }
      }
    },
    "/api/interview/submit-response": {
      "post": {
        "tags": [
          "PublicInterview"
        ],
        "requestBody": {
          "content": {
            "multipart/form-data": {
              "schema": {
                "type": "object",
                "properties": {
                  "SessionId": {
                    "type": "string",
                    "format": "uuid"
                  },
                  "QuestionOrder": {
                    "type": "integer",
                    "format": "int32"
                  },
                  "AudioResponse": {
                    "type": "string",
                    "format": "binary"
                  }
                }
              },
              "encoding": {
                "SessionId": {
                  "style": "form"
                },
                "QuestionOrder": {
                  "style": "form"
                },
                "AudioResponse": {
                  "style": "form"
                }
              }
            }
          }
        },
        "responses": {
          "200": {
            "description": "OK"
          }
        }
      }
    },
    "/api/interview/next-question": {
      "post": {
        "tags": [
          "PublicInterview"
        ],
        "requestBody": {
          "content": {
            "application/json": {
              "schema": {
                "$ref": "#/components/schemas/NextQuestionRequest"
              }
            },
            "text/json": {
              "schema": {
                "$ref": "#/components/schemas/NextQuestionRequest"
              }
            },
            "application/*+json": {
              "schema": {
                "$ref": "#/components/schemas/NextQuestionRequest"
              }
            }
          }
        },
        "responses": {
          "200": {
            "description": "OK"
          }
        }
      }
    },
    "/api/interview/sessions": {
      "get": {
        "tags": [
          "PublicInterview"
        ],
        "responses": {
          "200": {
            "description": "OK"
          }
        }
      }
    },
    "/api/interview/results/{sessionId}": {
      "get": {
        "tags": [
          "PublicInterview"
        ],
        "parameters": [
          {
            "name": "sessionId",
            "in": "path",
            "required": true,
            "schema": {
              "type": "string",
              "format": "uuid"
            }
          }
        ],
        "responses": {
          "200": {
            "description": "OK"
          }
        }
      }
    },
    "/api/interview/sessions/{sessionId}": {
      "delete": {
        "tags": [
          "PublicInterview"
        ],
        "parameters": [
          {
            "name": "sessionId",
            "in": "path",
            "required": true,
            "schema": {
              "type": "string",
              "format": "uuid"
            }
          }
        ],
        "responses": {
          "200": {
            "description": "OK"
          }
        }
      }
    }
  },
  "components": {
    "schemas": {
      "CompanyQuestionDto": {
        "type": "object",
        "properties": {
          "text": {
            "type": "string",
            "nullable": true
          },
          "idealAnswer": {
            "type": "string",
            "nullable": true
          },
          "difficulty": {
            "$ref": "#/components/schemas/Difficulty"
          }
        },
        "additionalProperties": false
      },
      "CreateAdminDto": {
        "required": [
          "email",
          "password"
        ],
        "type": "object",
        "properties": {
          "email": {
            "minLength": 1,
            "type": "string",
            "format": "email"
          },
          "password": {
            "minLength": 1,
            "type": "string"
          },
          "department": {
            "type": "string",
            "nullable": true
          }
        },
        "additionalProperties": false
      },
      "CreateCompanyInterviewRequest": {
        "type": "object",
        "properties": {
          "title": {
            "type": "string",
            "nullable": true
          },
          "questions": {
            "type": "array",
            "items": {
              "$ref": "#/components/schemas/CompanyQuestionDto"
            },
            "nullable": true
          },
          "questionsPerTier": {
            "type": "object",
            "properties": {
              "E": {
                "type": "integer",
                "format": "int32"
              },
              "D": {
                "type": "integer",
                "format": "int32"
              },
              "C": {
                "type": "integer",
                "format": "int32"
              },
              "B": {
                "type": "integer",
                "format": "int32"
              },
              "A": {
                "type": "integer",
                "format": "int32"
              }
            },
            "additionalProperties": false,
            "nullable": true
          },
          "candidateEmails": {
            "type": "array",
            "items": {
              "type": "string"
            },
            "nullable": true
          }
        },
        "additionalProperties": false
      },
      "CreateQuestionDto": {
        "type": "object",
        "properties": {
          "text": {
            "type": "string",
            "nullable": true
          },
          "idealAnswer": {
            "type": "string",
            "nullable": true
          },
          "audioUrl": {
            "type": "string",
            "nullable": true
          },
          "difficulty": {
            "$ref": "#/components/schemas/Difficulty"
          },
          "domainId": {
            "type": "string",
            "format": "uuid"
          }
        },
        "additionalProperties": false
      },
      "Difficulty": {
        "enum": [
          0,
          1,
          2,
          3,
          4
        ],
        "type": "integer",
        "format": "int32"
      },
      "InviteCandidatesRequest": {
        "type": "object",
        "properties": {
          "candidateEmails": {
            "type": "array",
            "items": {
              "type": "string"
            },
            "nullable": true
          }
        },
        "additionalProperties": false
      },
      "LoginDto": {
        "required": [
          "email",
          "password"
        ],
        "type": "object",
        "properties": {
          "email": {
            "minLength": 1,
            "type": "string"
          },
          "password": {
            "minLength": 1,
            "type": "string"
          }
        },
        "additionalProperties": false
      },
      "NextCandidateQuestionRequest": {
        "type": "object",
        "properties": {
          "sessionId": {
            "type": "string",
            "format": "uuid"
          }
        },
        "additionalProperties": false
      },
      "NextQuestionRequest": {
        "type": "object",
        "properties": {
          "sessionId": {
            "type": "string",
            "format": "uuid"
          }
        },
        "additionalProperties": false
      },
      "StartCandidateInterviewRequest": {
        "type": "object",
        "properties": {
          "candidateEmail": {
            "type": "string",
            "nullable": true
          }
        },
        "additionalProperties": false
      },
      "StartRequest": {
        "type": "object",
        "properties": {
          "domainId": {
            "type": "string",
            "format": "uuid"
          }
        },
        "additionalProperties": false
      },
      "UpdateDomainConfigurationDto": {
        "type": "object",
        "properties": {
          "questionsPerE": {
            "type": "integer",
            "format": "int32"
          },
          "questionsPerD": {
            "type": "integer",
            "format": "int32"
          },
          "questionsPerC": {
            "type": "integer",
            "format": "int32"
          },
          "questionsPerB": {
            "type": "integer",
            "format": "int32"
          },
          "questionsPerA": {
            "type": "integer",
            "format": "int32"
          }
        },
        "additionalProperties": false
      },
      "UpdateQuestionDto": {
        "type": "object",
        "properties": {
          "text": {
            "type": "string",
            "nullable": true
          },
          "idealAnswer": {
            "type": "string",
            "nullable": true
          },
          "audioUrl": {
            "type": "string",
            "nullable": true
          },
          "difficulty": {
            "$ref": "#/components/schemas/Difficulty"
          }
        },
        "additionalProperties": false
      },
      "UserType": {
        "enum": [
          0,
          1,
          2
        ],
        "type": "integer",
        "format": "int32"
      }
    },
    "securitySchemes": {
      "Bearer": {
        "type": "http",
        "description": "Please enter token",
        "scheme": "bearer",
        "bearerFormat": "JWT"
      }
    }
  }
}